eispac/__init__.py
eispac/conftest.py
eispac/core/__init__.py
eispac/core/eiscube.py
eispac/core/eisfitresult.py
eispac/core/eismap.py
eispac/core/export_fits.py
eispac/core/fit_spectra.py
eispac/core/fit_spectra_astropy.py
eispac/core/fitting_functions.py
eispac/core/generate_astropy_model.py
eispac/core/match_templates.py
eispac/core/mpfit.py
eispac/core/read_cube.py
eispac/core/read_fit.py
eispac/core/read_template.py
eispac/core/read_wininfo.py
eispac/core/save_fit.py
eispac/core/scale_guess.py
eispac/data/__init__.py
eispac/data/templates/__init__.py
eispac/data/templates/al_09_284_015.2c.template.h5
eispac/data/templates/al_09_284_015.2c.template.jpg
eispac/data/templates/ar_11_188_806.2c.template.h5
eispac/data/templates/ar_11_188_806.2c.template.jpg
eispac/data/templates/ar_11_188_806.3c.template.h5
eispac/data/templates/ar_11_188_806.3c.template.jpg
eispac/data/templates/ar_11_194_104.6c.template.h5
eispac/data/templates/ar_11_194_104.6c.template.jpg
eispac/data/templates/ar_14_187_964.1c.template.h5
eispac/data/templates/ar_14_187_964.1c.template.jpg
eispac/data/templates/ar_14_191_404.2c.template.h5
eispac/data/templates/ar_14_191_404.2c.template.jpg
eispac/data/templates/ar_14_194_396.1c.template.h5
eispac/data/templates/ar_14_194_396.1c.template.jpg
eispac/data/templates/ar_14_194_396.2c.template.h5
eispac/data/templates/ar_14_194_396.2c.template.jpg
eispac/data/templates/ar_14_194_396.4c.template.h5
eispac/data/templates/ar_14_194_396.4c.template.jpg
eispac/data/templates/ar_14_194_396.6c.template.h5
eispac/data/templates/ar_14_194_396.6c.template.jpg
eispac/data/templates/ca_14_183_457.1c.template.h5
eispac/data/templates/ca_14_183_457.1c.template.jpg
eispac/data/templates/ca_14_193_874.2c.template.h5
eispac/data/templates/ca_14_193_874.2c.template.jpg
eispac/data/templates/ca_14_193_874.4c.template.h5
eispac/data/templates/ca_14_193_874.4c.template.jpg
eispac/data/templates/ca_14_193_874.6c.template.h5
eispac-0.93.3.dist-info/LICENSE.txt
eispac-0.93.3.dist-info/METADATA
eispac-0.93.3.dist-info/WHEEL
eispac-0.93.3.dist-info/entry_points.txt
eispac-0.93.3.dist-info/top_level.txt
eispac-0.93.3.dist-info/RECORD
