Metadata-Version: 2.1
Name: eispac
Version: 0.93.3
Summary: Python analysis tools for Hinode / EIS data
Home-page: https://github.com/USNavalResearchLaboratory/eispac
Author: NRL EISPAC Development Team
License: MIT
Project-URL: Data, https://eis.nrl.navy.mil/
Project-URL: Documentation, https://eispac.readthedocs.io/
Keywords: solar,sun,physics,spectroscopy,Hinode,EIS
Platform: UNKNOWN
Classifier: Development Status :: 4 - Beta
Classifier: Intended Audience :: Science/Research
Classifier: Topic :: Scientific/Engineering :: Astronomy
Classifier: License :: OSI Approved :: MIT License
Classifier: Programming Language :: Python
Classifier: Programming Language :: Python :: 3
Classifier: Programming Language :: Python :: 3.7
Classifier: Programming Language :: Python :: 3.8
Classifier: Programming Language :: Python :: 3.9
Classifier: Operating System :: OS Independent
Requires-Python: >=3.7
Requires-Dist: numpy (>=1.18)
Requires-Dist: scipy (>=1.4)
Requires-Dist: matplotlib (>=3.1)
Requires-Dist: h5py (>=2.9)
Requires-Dist: astropy (>=3.1)
Requires-Dist: sunpy[map] (>=2.1)
Requires-Dist: ndcube (>=2.0.0)
Requires-Dist: parfive (>=1.5)
Requires-Dist: python-dateutil (>=2.8)
Provides-Extra: all
Requires-Dist: pytest (>=4.6.3) ; extra == 'all'
Provides-Extra: dev
Requires-Dist: pytest (>=4.6.3) ; extra == 'dev'
Requires-Dist: sphinx (==4.0.2) ; extra == 'dev'
Requires-Dist: sphinx-automodapi (>=0.13) ; extra == 'dev'
Requires-Dist: sphinx-rtd-theme ; extra == 'dev'
Provides-Extra: docs
Requires-Dist: sphinx (==4.0.2) ; extra == 'docs'
Requires-Dist: sphinx-automodapi (>=0.13) ; extra == 'docs'
Requires-Dist: sphinx-rtd-theme ; extra == 'docs'
Provides-Extra: test
Requires-Dist: pytest (>=4.6.3) ; extra == 'test'
